setup.py
cityweather/__init__.py
cityweather/cityweather.py
cityweather.egg-info/PKG-INFO
cityweather.egg-info/SOURCES.txt
cityweather.egg-info/dependency_links.txt
cityweather.egg-info/requires.txt
cityweather.egg-info/top_level.txt