Metadata-Version: 1.1
Name: cityweather
Version: 1.0.0
Summary: Weather forecast and details
Home-page: UNKNOWN
Author: Sidd
Author-email: UNKNOWN
License: MIT
Keywords: weather,forecast,openweather,temperature
Platform: UNKNOWN
Classifier: Development Status :: 3 - Alpha
Classifier: Intended Audience :: Developers
Classifier: Topic :: Software Development :: Build Tools
Classifier: License :: OSI Approved :: MIT License
Classifier: Programming Language :: Python :: 3.5
Classifier: Programming Language :: Python :: 3.6
Classifier: Programming Language :: Python :: 3.7
Classifier: Programming Language :: Python :: 3.8
